pywcsgrid2/__init__.py
pywcsgrid2/allsky_axes.py
pywcsgrid2/astropy_helper.py
pywcsgrid2/aux_artists.py
pywcsgrid2/axes_wcs.py
pywcsgrid2/floating_axes.py
pywcsgrid2/healpix_helper.py
pywcsgrid2/kapteyn_celestial.py
pywcsgrid2/locator_formatter.py
pywcsgrid2/wcs_helper.py
pywcsgrid2/wcs_transforms.py
pywcsgrid2-0.2.dist-info/entry_points.txt
pywcsgrid2-0.2.dist-info/LICENSE
pywcsgrid2-0.2.dist-info/LICENSE.txt
pywcsgrid2-0.2.dist-info/LICENSE_kapteyn.txt
pywcsgrid2-0.2.dist-info/WHEEL
pywcsgrid2-0.2.dist-info/METADATA
pywcsgrid2-0.2.dist-info/RECORD
