Metadata-Version: 2.1
Name: pywcsgrid2
Version: 0.2
Summary: a module to be used with matplotlib for displaying astronomical FITS images
Author-email: Jae-Joon Lee <lee.j.joon@gmail.com>
Requires-Python: >=3.5
Classifier: License :: OSI Approved :: MIT License
Requires-Dist: matplotlib >=3.5
Requires-Dist: astropy >=4
Requires-Dist: sphinx ; extra == "doc"
Project-URL: Home, http://leejjoon.github.io/pywcsgrid2/
Provides-Extra: doc
